{
  "summary": {
    "total_rules": 6,
    "generated_at": "2026-02-18T14:30:00Z",
    "num_simulations": 18000
  },
  "rules": [
    {
      "id": "rule_low_battery",
      "rule": "Low Battery Conservation",
      "discipline": "energy",
      "icon": "⚡",
      "condition": "battery_soc < 30% AND lap >= 40",
      "action": {
        "deploy_straight": 32,
        "deploy_corner": 28,
        "harvest": 82
      },
      "confidence": 0.92,
      "impact": {
        "baseline": 0.42,
        "uplift": 0.182,
      "expected_outcome": "Avoid SOC critical, finish P5 or better"
      },
      "rationale": "Heavy harvesting when SOC is critical creates enough buffer to prevent performance cliffs and thermal overload in braking zones.",
      "caveats": "Expect delta loss of 0.4s/lap while regen spike stabilises battery window.",
      "heatmap": [
        { "lap": 38, "battery": 34, "effectiveness": 0.45 },
        { "lap": 42, "battery": 28, "effectiveness": 0.72 },
        { "lap": 46, "battery": 24, "effectiveness": 0.88 },
        { "lap": 50, "battery": 22, "effectiveness": 0.94 },
        { "lap": 54, "battery": 20, "effectiveness": 0.90 }
      ]
    },
    {
      "id": "rule_mid_race_buffer",
      "rule": "Mid-Race Energy Buffer",
      "discipline": "energy",
      "icon": "🧮",
      "condition": "lap 18-34 AND tyre_life > 45%",
      "action": {
        "deploy_straight": 52,
        "deploy_corner": 46,
        "harvest": 64
      },
      "confidence": 0.78,
      "impact": {
        "baseline": 0.48,
        "uplift": 0.126,
        "expected_outcome": "Build +9% SOC buffer without losing track position"
      },
      "rationale": "Balanced deploy/harvest loop targeting nets positive SOC swing while tyre carcass temps remain in safe window.",
      "heatmap": [
        { "lap": 20, "battery": 58, "effectiveness": 0.71 },
        { "lap": 26, "battery": 54, "effectiveness": 0.76 },
        { "lap": 30, "battery": 50, "effectiveness": 0.82 },
        { "lap": 34, "battery": 46, "effectiveness": 0.79 }
      ]
    },
    {
      "id": "rule_final_stint_attack",
      "rule": "Final Stint Attack",
      "discipline": "energy",
      "icon": "🏁",
      "condition": "lap >= 45 AND battery_soc > 40%",
      "action": {
        "deploy_straight": 94,
        "deploy_corner": 82,
        "harvest": 28
      },
      "confidence": 0.86,
      "impact": {
        "baseline": 0.51,
        "uplift": 0.168,
        "expected_outcome": "Gain +0.6s delta over 5 laps, overtake probability +23%"
      },
      "rationale": "Converts saved electric energy into straight-line delta while tyre surface still in working range.",
      "caveats": "Battery dip exposes driver to vulnerability if safety car deploys immediately after attack.",
      "heatmap": [
        { "lap": 46, "battery": 44, "effectiveness": 0.63 },
        { "lap": 50, "battery": 41, "effectiveness": 0.88 },
        { "lap": 53, "battery": 38, "effectiveness": 0.92 },
        { "lap": 56, "battery": 35, "effectiveness": 0.85 }
      ]
    },
    {
      "id": "rule_rain_offset",
      "rule": "Rain Offset Harvest",
      "discipline": "tyre",
      "icon": "🌧️",
      "condition": "rain Forecasted AND lap < 35",
      "action": {
        "deploy_straight": 44,
        "deploy_corner": 38,
        "harvest": 72
      },
      "confidence": 0.74,
      "impact": {
        "baseline": 0.37,
        "uplift": 0.144,
        "expected_outcome": "Arrive at pit-stop window with +12% SOC headroom"
      },
      "rationale": "Pre-emptive harvest under incoming rain allows for aggressive push on out-lap after tyre change.",
      "heatmap": [
        { "lap": 12, "battery": 70, "effectiveness": 0.42 },
        { "lap": 20, "battery": 64, "effectiveness": 0.66 },
        { "lap": 28, "battery": 58, "effectiveness": 0.72 },
        { "lap": 34, "battery": 50, "effectiveness": 0.69 }
      ]
    },
    {
      "id": "rule_undercut_charge",
      "rule": "Undercut Charge Mode",
      "discipline": "fuel",
      "icon": "⛽",
      "condition": "gap_ahead < 1.5s AND tyres fresh",
      "action": {
        "deploy_straight": 76,
        "deploy_corner": 64,
        "harvest": 42
      },
      "confidence": 0.81,
      "impact": {
        "baseline": 0.44,
        "uplift": 0.159,
        "expected_outcome": "Execute undercut with +0.7s delta on out-lap"
      },
      "rationale": "Short burst rich mix combined with high deploy closes track gap prior to pit entry.",
      "heatmap": [
        { "lap": 16, "battery": 62, "effectiveness": 0.48 },
        { "lap": 24, "battery": 58, "effectiveness": 0.70 },
        { "lap": 32, "battery": 53, "effectiveness": 0.79 },
        { "lap": 40, "battery": 47, "effectiveness": 0.68 }
      ]
    },
    {
      "id": "rule_safety_car_reset",
      "rule": "Safety Car Reset",
      "discipline": "aero",
      "icon": "🚨",
      "condition": "safety_car_risk > 60% AND battery_soc > 55%",
      "action": {
        "deploy_straight": 48,
        "deploy_corner": 40,
        "harvest": 70
      },
      "confidence": 0.68,
      "impact": {
        "baseline": 0.39,
        "uplift": 0.121,
        "expected_outcome": "Hold tyre temp and energy buffer ready for restart jump"
      },
      "rationale": "Builds SOC cushion and keeps tyre core temp stable ahead of restart compression.",
      "caveats": "Can concede 0.3s/lap to direct rivals during conservation phase.",
      "heatmap": [
        { "lap": 10, "battery": 72, "effectiveness": 0.36 },
        { "lap": 18, "battery": 68, "effectiveness": 0.58 },
        { "lap": 26, "battery": 63, "effectiveness": 0.73 },
        { "lap": 34, "battery": 59, "effectiveness": 0.69 }
      ]
    }
  ]
}
